mask_in_situ/__init__.py
mask_in_situ/cli.py
mask_in_situ/core.py
mask_in_situ-0.1.2.dist-info/LICENSE
mask_in_situ-0.1.2.dist-info/METADATA
mask_in_situ-0.1.2.dist-info/WHEEL
mask_in_situ-0.1.2.dist-info/entry_points.txt
mask_in_situ-0.1.2.dist-info/top_level.txt
mask_in_situ-0.1.2.dist-info/RECORD
