Metadata-Version: 2.1
Name: mask-in-situ
Version: 0.1.2
Summary: A simple tool for encrypting (only) the secrets inside text files
Home-page: https://github.com/jamesscottbrown/mask-in-situ
Author: James Scott-Brown
Author-email: james@jamesscottbrown.com
License: BSD 3-Clause License
Project-URL: Bug Tracker, https://github.com/jamesscottbrown/mask-in-situ
Platform: UNKNOWN
Classifier: Programming Language :: Python :: 3
Classifier: License :: OSI Approved :: BSD License
Classifier: Operating System :: OS Independent
Requires-Python: >=3.6
License-File: LICENSE
Requires-Dist: click
Requires-Dist: cryptography
